setup.cfg
setup.py
HEpigram.egg-info/PKG-INFO
HEpigram.egg-info/SOURCES.txt
HEpigram.egg-info/dependency_links.txt
HEpigram.egg-info/entry_points.txt
HEpigram.egg-info/top_level.txt
hepigram/__init__.py
hepigram/app.py
hepigram/git_handler.py
hepigram/linter.py
hepigram/mkdocs.py
hepigram/utils.py
hepigram/yaml_parser.py