Metadata-Version: 1.1
Name: HEpigram
Version: 0.1
Summary: HEpigram provides a friendly interface for documents that need to be generated/compiled by tools like MkDocs.
Home-page: https://dev.hackerexperience.com/diffusion/HEPG/
Author: Renato Massaro
Author-email: renato@hackerexperience.com
License: MIT
Download-URL: https://dev.hackerexperience.com/diffusion/HEPG/browse/master/;0.1
Keywords: documentation
Platform: UNKNOWN
